LICENSE
README.md
setup.py
CVE_2024_0235.egg-info/PKG-INFO
CVE_2024_0235.egg-info/SOURCES.txt
CVE_2024_0235.egg-info/dependency_links.txt
CVE_2024_0235.egg-info/entry_points.txt
CVE_2024_0235.egg-info/requires.txt
CVE_2024_0235.egg-info/top_level.txt
cve20240235/main.py
cve20240235/includes/__init__.py
cve20240235/includes/bot.py
cve20240235/includes/filereader.py
cve20240235/includes/scan.py
cve20240235/includes/writefile.py
cve20240235/utils/__init__.py
cve20240235/utils/configure.py
cve20240235/utils/const.py
cve20240235/utils/helpers.py
cve20240235/utils/status.py